scrape_and_ntfy-0.1.2.dist-info/METADATA
scrape_and_ntfy-0.1.2.dist-info/WHEEL
scrape_and_ntfy-0.1.2.dist-info/entry_points.txt
scrape_and_ntfy-0.1.2.dist-info/licenses/LICENSE
scrape_and_ntfy/__init__.py
scrape_and_ntfy/__main__.py
scrape_and_ntfy/scraping/__init__.py
scrape_and_ntfy/scraping/notifier.py
scrape_and_ntfy/scraping/scraper.py
scrape_and_ntfy/utils/__init__.py
scrape_and_ntfy/utils/cli_args.py
scrape_and_ntfy/utils/db.py
scrape_and_ntfy/utils/logging.py
scrape_and_ntfy/utils/utils.py
scrape_and_ntfy-0.1.2.dist-info/RECORD
