Metadata-Version: 2.1
Name: scrape-and-ntfy
Version: 0.1.2
Summary: An extremely customizable web scraper with a modular notification system and persistent storage via SQLite.
Keywords: web,scraper,ntfy,webhooks,docker
Author-Email: slashtechno <77907286+slashtechno@users.noreply.github.com>, mikeymoo5 <53538532+Mikeymoo5@users.noreply.github.com>
Classifier: License :: OSI Approved :: MIT License
Classifier: Programming Language :: Python
Requires-Python: >=3.11
Requires-Dist: dataset>=1.6.2
Requires-Dist: loguru>=0.7.2
Requires-Dist: python-dotenv>=1.0.1
Requires-Dist: selenium>=4.21.0
Requires-Dist: httpx>=0.27.0
Requires-Dist: toml>=0.10.2
